Metadata-Version: 1.0
Name: iplOss
Version: 0.0.2
Summary: iPayLinks FileServer tool
Home-page: UNKNOWN
Author: UNKNOWN
Author-email: UNKNOWN
License: UNKNOWN
Platform: UNKNOWN
